balpy/__init__.py
balpy/abi/ERC20.json
balpy/balancer-deployments/.eslintignore
balpy/balancer-deployments/.eslintrc.js
balpy/balancer-deployments/.git
balpy/balancer-deployments/.github/PULL_REQUEST_TEMPLATE/deployment-preparation-template.md
balpy/balancer-deployments/.github/PULL_REQUEST_TEMPLATE/deployment-template.md
balpy/balancer-deployments/.github/actions/check-network-action-ids/action.yml
balpy/balancer-deployments/.github/actions/check-network-deployments/action.yml
balpy/balancer-deployments/.github/actions/setup/action.yml
balpy/balancer-deployments/.github/pull_request_template.md
balpy/balancer-deployments/.github/workflows/ci.yml
balpy/balancer-deployments/.github/workflows/deployment-checks.yml
balpy/balancer-deployments/.gitignore
balpy/balancer-deployments/.gitmodules
balpy/balancer-deployments/.mocharc.json
balpy/balancer-deployments/.nvmrc
balpy/balancer-deployments/.prettierrc.json
balpy/balancer-deployments/.solhint.json
balpy/balancer-deployments/.yarn/plugins/@yarnpkg/plugin-typescript.cjs
balpy/balancer-deployments/.yarn/plugins/@yarnpkg/plugin-version.cjs
balpy/balancer-deployments/.yarn/plugins/@yarnpkg/plugin-workspace-tools.cjs
balpy/balancer-deployments/.yarn/releases/yarn-4.0.0-rc.42.cjs
balpy/balancer-deployments/.yarn/versions/1dfc32f3.yml
balpy/balancer-deployments/.yarnrc.yml
balpy/balancer-deployments/CHANGELOG.md
balpy/balancer-deployments/DEPLOYING.md
balpy/balancer-deployments/LICENSE
balpy/balancer-deployments/README.md
balpy/balancer-deployments/action-ids/arbitrum/action-ids.json
balpy/balancer-deployments/action-ids/arbitrum/expected-collisions.json
balpy/balancer-deployments/action-ids/avalanche/action-ids.json
balpy/balancer-deployments/action-ids/avalanche/expected-collisions.json
balpy/balancer-deployments/action-ids/base/action-ids.json
balpy/balancer-deployments/action-ids/bsc/action-ids.json
balpy/balancer-deployments/action-ids/fantom/action-ids.json
balpy/balancer-deployments/action-ids/gnosis/action-ids.json
balpy-0.0.0a85.dist-info/LICENSE
balpy-0.0.0a85.dist-info/WHEEL
balpy-0.0.0a85.dist-info/METADATA
balpy-0.0.0a85.dist-info/RECORD
