Metadata-Version: 2.1
Name: balpy
Version: 0.0.0a85
Summary: Balancer V2 Python API
License: GNU GPL 3
Author: Greg
Author-email: greg@threerocks.io
Requires-Python: >=3.9,<4.0
Classifier: License :: Other/Proprietary License
Classifier: Programming Language :: Python :: 3
Classifier: Programming Language :: Python :: 3.10
Classifier: Programming Language :: Python :: 3.9
Requires-Dist: Cython (==0.29.24)
Requires-Dist: cytoolz (==0.11.2)
Requires-Dist: eth-abi (==2.1.1)
Requires-Dist: gql (==2.0.0)
Requires-Dist: jstyleson (==0.0.2)
Requires-Dist: multicaller (>=0.0.0a10)
Requires-Dist: requests (==2.25.1)
Requires-Dist: web3 (==5.19.0)
